omniTask/__init__.py
omniTask/cache/__init__.py
omniTask/cache/cache_interface.py
omniTask/cache/cache_key_generator.py
omniTask/cache/file_cache.py
omniTask/cache/memory_cache.py
omniTask/core/registry.py
omniTask/core/task.py
omniTask/core/template.py
omniTask/core/workflow.py
omniTask/models/task_group.py
omniTask/models/task_result.py
omniTask/utils/logging.py
omniTask/utils/path_parser.py
omniTask/utils/workflow_checker.py
omnitask-1.0.0.dist-info/licenses/LICENSE
omnitask-1.0.0.dist-info/METADATA
omnitask-1.0.0.dist-info/WHEEL
omnitask-1.0.0.dist-info/top_level.txt
omnitask-1.0.0.dist-info/RECORD
