Metadata-Version: 2.4
Name: omniTask
Version: 1.0.0
Summary: A powerful Python-based workflow automation tool
Home-page: https://github.com/sarperavci/omniTask
Author: SARPER AVCI
Author-email: SARPER AVCI <sarperavci20@gmail.com>
License: MIT
Project-URL: Homepage, https://github.com/sarperavci/omniTask
Project-URL: Repository, https://github.com/sarperavci/omniTask.git
Classifier: Development Status :: 3 - Alpha
Classifier: Intended Audience :: Developers
Classifier: License :: OSI Approved :: MIT License
Classifier: Programming Language :: Python :: 3
Classifier: Programming Language :: Python :: 3.8
Classifier: Programming Language :: Python :: 3.9
Classifier: Programming Language :: Python :: 3.10
Classifier: Programming Language :: Python :: 3.11
Requires-Python: >=3.8
License-File: LICENSE
Requires-Dist: PyYAML>=6.0
Dynamic: author
Dynamic: home-page
Dynamic: license-file
Dynamic: requires-python
